qlsc/__init__.py
qlsc/generate.py
qlsc/q3c.cpython-38-darwin.so
qlsc/qlsc_base.py
qlsc/qlsc_functions.py
qlsc/utilities.py
qlsc/version.py
qlsc/c_code/qlsc_c_module.c
qlsc/c_code/q3c/common.h
qlsc/c_code/q3c/my_bits.h
qlsc/c_code/q3c/q3c_poly.c
qlsc/c_code/q3c/q3cube.c
qlsc-1.0.6.dist-info/METADATA
qlsc-1.0.6.dist-info/WHEEL
qlsc-1.0.6.dist-info/top_level.txt
qlsc-1.0.6.dist-info/RECORD
