Metadata-Version: 2.1
Name: qlsc
Version: 1.0.6
Summary: A Python implementation of the quadrilateralized spherical cube scheme.
Home-page: https://github.com/demitri/qlsc
Author: Demitri Muna
Author-email: demitri@trillianverse.org
License: UNKNOWN
Project-URL: Documentation, https://qlsc.readthedocs.io/en/latest/
Project-URL: Source Code, https://github.com/demitri/qlsc
Platform: UNKNOWN
Requires-Python: >=3.6
